odoo/addons/sale_project_link/LICENSE
odoo/addons/sale_project_link/README.rst
odoo/addons/sale_project_link/__init__.py
odoo/addons/sale_project_link/__manifest__.py
odoo/addons/sale_project_link/images/screen.png
odoo/addons/sale_project_link/models/__init__.py
odoo/addons/sale_project_link/models/sale_order_line.py
odoo/addons/sale_project_link/readme/CONTRIBUTORS.md
odoo/addons/sale_project_link/readme/DESCRIPTION.md
odoo/addons/sale_project_link/readme/USAGE.md
odoo/addons/sale_project_link/static/description/icon.png
odoo/addons/sale_project_link/static/description/index.html
odoo/addons/sale_project_link/tests/TEST_INSTRUCTIONS.rst
odoo/addons/sale_project_link/views/sale_order_views.xml
odoo_addon_sale_project_link-16.0.1.0.0.dist-info/METADATA
odoo_addon_sale_project_link-16.0.1.0.0.dist-info/WHEEL
odoo_addon_sale_project_link-16.0.1.0.0.dist-info/top_level.txt
odoo_addon_sale_project_link-16.0.1.0.0.dist-info/RECORD
